obsidian_mcp/__init__.py
obsidian_mcp/configure.py
obsidian_mcp/constants.py
obsidian_mcp/server.py
obsidian_mcp/models/__init__.py
obsidian_mcp/models/obsidian.py
obsidian_mcp/tools/__init__.py
obsidian_mcp/tools/image_management.py
obsidian_mcp/tools/link_management.py
obsidian_mcp/tools/note_management.py
obsidian_mcp/tools/organization.py
obsidian_mcp/tools/search_discovery.py
obsidian_mcp/tools/view_note_images.py
obsidian_mcp/utils/__init__.py
obsidian_mcp/utils/filesystem.py
obsidian_mcp/utils/persistent_index.py
obsidian_mcp/utils/validation.py
obsidian_mcp/utils/validators.py
obsidian_mcp-2.1.2.dist-info/licenses/LICENSE
obsidian_mcp-2.1.2.dist-info/METADATA
obsidian_mcp-2.1.2.dist-info/WHEEL
obsidian_mcp-2.1.2.dist-info/entry_points.txt
obsidian_mcp-2.1.2.dist-info/top_level.txt
obsidian_mcp-2.1.2.dist-info/RECORD
