Metadata-Version: 2.4
Name: obsidian-mcp
Version: 2.1.2
Summary: MCP server for interacting with Obsidian vaults through direct filesystem access
Author-email: Nate Strong <nathanstrong.fx@gmail.com>
License-Expression: MIT
Project-URL: Homepage, https://github.com/natestrong/obsidian-mcp
Project-URL: Repository, https://github.com/natestrong/obsidian-mcp
Project-URL: Issues, https://github.com/natestrong/obsidian-mcp/issues
Keywords: mcp,obsidian,fastmcp,llm,ai,notes,knowledge-management
Classifier: Development Status :: 4 - Beta
Classifier: Intended Audience :: Developers
Classifier: Programming Language :: Python :: 3
Classifier: Programming Language :: Python :: 3.10
Classifier: Programming Language :: Python :: 3.11
Classifier: Programming Language :: Python :: 3.12
Requires-Python: >=3.10
License-File: LICENSE
Requires-Dist: fastmcp>=2.8.1
Requires-Dist: python-dotenv>=1.0.0
Requires-Dist: pydantic>=2.0.0
Requires-Dist: aiofiles>=23.0.0
Requires-Dist: pyyaml>=6.0.0
Requires-Dist: pillow>=10.0.0
Requires-Dist: aiosqlite>=0.19.0
Provides-Extra: dev
Requires-Dist: pytest>=7.0.0; extra == "dev"
Requires-Dist: pytest-asyncio>=0.21.0; extra == "dev"
Requires-Dist: pytest-mock>=3.10.0; extra == "dev"
Dynamic: license-file
